csrspy/__init__.py
csrspy/enums.py
csrspy/factories.py
csrspy/main.py
csrspy/utils.py
csrspy-0.7.0.dist-info/METADATA
csrspy-0.7.0.dist-info/WHEEL
csrspy-0.7.0.dist-info/RECORD
